soildx_fastapi_jwt_auth/__init__.py
soildx_fastapi_jwt_auth/jwt_auth.py
soildx_fastapi_jwt_auth-0.0.6.dist-info/METADATA
soildx_fastapi_jwt_auth-0.0.6.dist-info/WHEEL
soildx_fastapi_jwt_auth-0.0.6.dist-info/top_level.txt
soildx_fastapi_jwt_auth-0.0.6.dist-info/RECORD
